waveshapes/__init__.py
waveshapes/scene.py
waveshapes-0.1.0.dist-info/LICENSE
waveshapes-0.1.0.dist-info/METADATA
waveshapes-0.1.0.dist-info/WHEEL
waveshapes-0.1.0.dist-info/top_level.txt
waveshapes-0.1.0.dist-info/RECORD
