Metadata-Version: 2.1
Name: waveshapes
Version: 0.1.0
Summary: A Python library to generate and manipulate audio.
Author: Tom Vincent
Author-email: TomVincentCode@gmail.com
License: UNKNOWN
Platform: UNKNOWN
Classifier: Programming Language :: Python :: 3
Classifier: License :: OSI Approved :: MIT License
Requires-Python: >=3.10
License-File: LICENSE
